dejan/__init__.py
dejan/authority.py
dejan/cli.py
dejan/linkbert.py
dejan/roo.py
dejan/veczip.py
dejan/apps/__init__.py
dejan/apps/authority_app.py
dejan/apps/linkbert_app.py
dejan/apps/roo_app.py
dejan/apps/veczip_app.py
dejan-1.3.dist-info/LICENSE
dejan-1.3.dist-info/METADATA
dejan-1.3.dist-info/WHEEL
dejan-1.3.dist-info/entry_points.txt
dejan-1.3.dist-info/top_level.txt
dejan-1.3.dist-info/RECORD
