Metadata-Version: 2.1
Name: dejan
Version: 1.3
Summary: Machine learning utilities by DEJAN.
Home-page: https://github.com/dejanmarketing/dejan
Author: DEJAN
Author-email: enquiries@dejanmarketing.com
Classifier: Programming Language :: Python :: 3
Classifier: License :: OSI Approved :: MIT License
Classifier: Operating System :: OS Independent
Requires-Python: >=3.6
License-File: LICENSE
Requires-Dist: requests
Requires-Dist: pandas
Requires-Dist: transformers
Requires-Dist: torch
Requires-Dist: click
